cli/__init__.py
cli/main.py
hang_up_an_autumn_moon-0.3.2.dist-info/LICENSE
hang_up_an_autumn_moon-0.3.2.dist-info/METADATA
hang_up_an_autumn_moon-0.3.2.dist-info/WHEEL
hang_up_an_autumn_moon-0.3.2.dist-info/entry_points.txt
hang_up_an_autumn_moon-0.3.2.dist-info/top_level.txt
hang_up_an_autumn_moon-0.3.2.dist-info/RECORD
