Metadata-Version: 2.1
Name: hang-up-an-autumn-moon
Version: 0.3.2
Summary: UNKNOWN
Home-page: UNKNOWN
License: UNKNOWN
Platform: UNKNOWN
Requires-Dist: Click
Requires-Dist: simple-term-menu
Requires-Dist: prettytable
Requires-Dist: numpy
